repr/__init__.py
repr/__main__.py
repr/api.py
repr/auth.py
repr/cli.py
repr/config.py
repr/discovery.py
repr/doctor.py
repr/extractor.py
repr/hooks.py
repr/keychain.py
repr/llm.py
repr/openai_analysis.py
repr/privacy.py
repr/storage.py
repr/telemetry.py
repr/templates.py
repr/tools.py
repr/ui.py
repr/updater.py
repr_cli-0.2.16.dist-info/licenses/LICENSE
repr_cli-0.2.16.dist-info/METADATA
repr_cli-0.2.16.dist-info/WHEEL
repr_cli-0.2.16.dist-info/entry_points.txt
repr_cli-0.2.16.dist-info/top_level.txt
repr_cli-0.2.16.dist-info/RECORD
