Metadata-Version: 2.4
Name: repr-cli
Version: 0.2.16
Summary: A beautiful, privacy-first CLI that analyzes your code repositories and generates a compelling developer profile
Author-email: Repr <hello@repr.dev>
License: MIT License
Project-URL: Homepage, https://repr.dev
Project-URL: Documentation, https://repr.dev/docs
Project-URL: Repository, https://github.com/repr-app/cli
Keywords: cli,developer,profile,git,analysis,repr
Classifier: Development Status :: 4 - Beta
Classifier: Environment :: Console
Classifier: Intended Audience :: Developers
Classifier: Operating System :: OS Independent
Classifier: Programming Language :: Python :: 3
Classifier: Programming Language :: Python :: 3.10
Classifier: Programming Language :: Python :: 3.11
Classifier: Programming Language :: Python :: 3.12
Classifier: Topic :: Software Development :: Version Control :: Git
Requires-Python: >=3.10
License-File: LICENSE
Requires-Dist: typer>=0.9.0
Requires-Dist: rich>=13.0.0
Requires-Dist: gitpython>=3.1.0
Requires-Dist: pygments>=2.16.0
Requires-Dist: httpx>=0.25.0
Requires-Dist: openai>=1.0.0
Requires-Dist: keyring>=24.0.0
Requires-Dist: pydantic>=2.0.0
Provides-Extra: dev
Requires-Dist: pytest>=7.0.0; extra == "dev"
Requires-Dist: pytest-asyncio>=0.21.0; extra == "dev"
Requires-Dist: black>=23.0.0; extra == "dev"
Requires-Dist: ruff>=0.1.0; extra == "dev"
Dynamic: license-file
